gmpyinfr_dbutils/__init__.py
gmpyinfr_dbutils/db/__init__.py
gmpyinfr_dbutils/db/manager.py
gmpyinfr_dbutils/utils/__init__.py
gmpyinfr_dbutils/utils/utils.py
gmpyinfr_dbutils-0.0.7.dist-info/LICENSE
gmpyinfr_dbutils-0.0.7.dist-info/METADATA
gmpyinfr_dbutils-0.0.7.dist-info/WHEEL
gmpyinfr_dbutils-0.0.7.dist-info/top_level.txt
gmpyinfr_dbutils-0.0.7.dist-info/RECORD
