Metadata-Version: 2.1
Name: gmpyinfr-dbutils
Version: 0.0.7
Summary: Infraestrutura dbutils python de uma equipe de Ciência de Dados
Home-page: UNKNOWN
Author: Alex Newman
Author-email: a.newmanvs@gmail.com
License: UNKNOWN
Platform: UNKNOWN
Classifier: Development Status :: 5 - Production/Stable
Classifier: Environment :: Console
Classifier: Programming Language :: Python
Classifier: Programming Language :: Python :: 3
Classifier: Programming Language :: Python :: 3 :: Only
Classifier: Programming Language :: Python :: 3.7
Classifier: Operating System :: Unix
Requires-Python: >=3.6
Requires-Dist: turbodbc (==4.1.2)
Requires-Dist: pyarrow (>=3.0.0)
Requires-Dist: pandas (>=1.0.0)
